MANIFEST.in
README.txt
etm
etmtk
setup.py
etmTk/CHANGES
etmTk/__init__.py
etmTk/data.py
etmTk/dialog.py
etmTk/etm.1
etmTk/etm.appdata.xml
etmTk/etm.desktop
etmTk/etm.xpm
etmTk/etmlogo.gif
etmTk/etmlogo.icns
etmTk/etmlogo.ico
etmTk/v.py
etmTk/version.py
etmTk/view.py
etmTk/help/UserManual.html
etmTk/icons/etmlogo.gif
etmTk/icons/icon_check.gif
etmTk/icons/icon_check_green.gif
etmTk/icons/icon_check_red.gif
etmTk/icons/icon_clock.gif
etmTk/icons/icon_pause.gif
etmTk/icons/icon_play.gif
etmTk/icons/icon_plus.gif
etmTk/icons/icon_refresh.gif
etmTk/icons/icon_search.gif
etmTk/icons/icon_settings.gif
etmTk/icons/icon_stop.gif
etmtk/data.py
etmtk/v.py
etmtk.egg-info/PKG-INFO
etmtk.egg-info/SOURCES.txt
etmtk.egg-info/dependency_links.txt
etmtk.egg-info/not-zip-safe
etmtk.egg-info/requires.txt
etmtk.egg-info/top_level.txt