Metadata-Version: 1.1
Name: etmtk
Version: 3.2.24
Summary: event and task manager
Home-page: http://people.duke.edu/~dgraham/etmtk
Author: Daniel A Graham
Author-email: daniel.graham@duke.edu
License: License :: OSI Approved :: GNU General Public License (GPL)
Platform: Any
Classifier: Development Status :: 5 - Production/Stable
Classifier: Environment :: Console
Classifier: Environment :: MacOS X
Classifier: Environment :: Win32 (MS Windows)
Classifier: Environment :: X11 Applications
Classifier: Intended Audience :: End Users/Desktop
Classifier: License :: OSI Approved :: GNU General Public License (GPL)
Classifier: Operating System :: MacOS :: MacOS X
Classifier: Operating System :: Microsoft :: Windows :: Windows Vista
Classifier: Operating System :: Microsoft :: Windows :: Windows 7
Classifier: Operating System :: OS Independent
Classifier: Operating System :: POSIX
Classifier: Operating System :: POSIX :: Linux
Classifier: Programming Language :: Python
Classifier: Programming Language :: Python :: 2.7
Classifier: Programming Language :: Python :: 3.3
Classifier: Programming Language :: Python :: 3.4
Classifier: Programming Language :: Python :: 3.5
Classifier: Topic :: Office/Business
Classifier: Topic :: Office/Business :: News/Diary
Classifier: Topic :: Office/Business :: Scheduling
